Workbook
Name Slicer_Department: #N/A
Name Slicer_Gender: #N/A
Name Slicer_OverTime: #N/A

Sheet Dashboard
A2: HR Employee Attrition Analysis Dashboard
A3: Total Employees | D3: Employees Left | G3: Active Employees | J3: Avg Monthly Income | M3: Attrition Rate
A4: =Pivot_Analysis!A4 -> 1470 | D4: =Pivot_Analysis!D4 -> 237 | G4: =Pivot_Analysis!G4 -> 1233 | J4: =Pivot_Analysis!J4 -> 6502.9313 | M4: =Pivot_Analysis!M4 -> 0.16122449

Sheet Business_Insights
A1: HR Employee Attrition Analysis
A3: Objective : Analyze employee attrition patterns by department, job role, age group, salary band, gender, and overtime status to identify key turnover drivers.
A6: Insight Area | B6: Observation | C6: Business Meaning
A7: Overall Attrition | B7: 237 employees left out of 1470 employees, giving an attrition rate of 16.12%. | C7: The company has a noticeable employee turnover issue.
A9: Department | B9: Research & Development recorded the largest number of departures (133), but Sales had the highest departmental attrition rate at 20.63%, compared with 13.84% in R&D. | C9: R&D needs deeper review because it contributes the largest attrition count.
A11: Job Role | B11: Laboratory Technicians recorded the most departures (62), while Sales Representatives showed the highest attrition rate at 39.76%, indicating a substantially higher retention risk within that role. | C11: These roles may need better retention plans, salary review, or workload analysis.
A13: Age Group | B13: Employees aged 25–34 recorded the most departures (112), while employees under 25 had the highest attrition rate at 39.18%. | C13: Early-career employees may be leaving for better growth or compensation.
A15: Salary Band | B15: Low-salary employees had the highest attrition rate at 28.61%, compared with 12.03% for medium-salary and 10.80% for high-salary employees. | C15: Compensation may be one major reason for employee exits.
A17: Overtime | B17: Employees working overtime had an attrition rate of 30.53%, compared with 10.44% among employees not working overtime, indicating a strong association between overtime and attrition. | C17: If attrition increases for overtime employees, workload balance is a major concern.
A21: Recommendation | B21: Reason
A22: Review compensation for low salary employees. | B22: Low salary band has higher attrition.
A24: Improve career growth programs for employees aged 25–34. | B24: This group shows the highest leaving trend.
A26: Conduct role-specific retention analysis for Sales Representatives, Laboratory Technicians, and Human Resources. | B26: These roles have the highest attrition rates at 39.76%, 23.94%, and 23.08%, respectively.
A28: Monitor overtime workload. | B28: Employees working overtime may be at higher risk of leaving.
A30: Create department-level retention plans for R&D and Sales. | B30: These departments contribute more attrition cases.
A32: Investigate compensation, workload, career progression, and management factors affecting Sales Representatives and other high-attrition roles. | B32: Sales Representatives have the highest job-role attrition rate at 39.76%, indicating the need for deeper root-cause analysis.
A36: Conclusion:
A37: The analysis identified an overall employee attrition rate of 16.12%, with higher attrition concentrated among specific employee groups. Employees under 25 had the highest age-group attrition rate at 39.18%, Sales Representatives recorded the highest job-role attrition rate at 39.76%, and low-salary employees experienced a 28.61% attrition rate. Employees working overtime also showed substantially higher attrition at 30.53%, compared with 10.44% among employees not working overtime. At the department level, Sales had the highest attrition rate at 20.63%. These findings suggest that retention efforts should prioritize younger employees, low-salary groups, high-risk job roles, and employees working overtime while further investigating the underlying factors contributing to turnover.

Sheet Raw_Data
A1: Age | B1: Attrition | C1: BusinessTravel | D1: DailyRate | E1: Department | F1: DistanceFromHome | G1: Education | H1: EducationField | I1: EmployeeCount | J1: EmployeeNumber | K1: EnvironmentSatisfaction | L1: Gender | M1: HourlyRate | N1: JobInvolvement | O1: JobLevel | P1: JobRole | Q1: JobSatisfaction | R1: MaritalStatus | S1: MonthlyIncome | T1: MonthlyRate | U1: NumCompaniesWorked | V1: Over18 | W1: OverTime | X1: PercentSalaryHike | Y1: PerformanceRating | Z1: RelationshipSatisfaction | AA1: StandardHours | AB1: StockOptionLevel | AC1: TotalWorkingYears | AD1: TrainingTimesLastYear | AE1: WorkLifeBalance | AF1: YearsAtCompany | AG1: YearsInCurrentRole | AH1: YearsSinceLastPromotion | AI1: YearsWithCurrManager
A2: 41 | B2: Yes | C2: Travel_Rarely | D2: 1102 | E2: Sales | F2: 1 | G2: 2 | H2: Life Sciences | I2: 1 | J2: 1 | K2: 2 | L2: Female | M2: 94 | N2: 3 | O2: 2 | P2: Sales Executive | Q2: 4 | R2: Single | S2: 5993 | T2: 19479 | U2: 8 | V2: Y | W2: Yes | X2: 11 | Y2: 3 | Z2: 1 | AA2: 80 | AB2: 0 | AC2: 8 | AD2: 0 | AE2: 1 | AF2: 6 | AG2: 4 | AH2: 0 | AI2: 5
A3: 49 | B3: No | C3: Travel_Frequently | D3: 279 | E3: Research & Development | F3: 8 | G3: 1 | H3: Life Sciences | I3: 1 | J3: 2 | K3: 3 | L3: Male | M3: 61 | N3: 2 | O3: 2 | P3: Research Scientist | Q3: 2 | R3: Married | S3: 5130 | T3: 24907 | U3: 1 | V3: Y | W3: No | X3: 23 | Y3: 4 | Z3: 4 | AA3: 80 | AB3: 1 | AC3: 10 | AD3: 3 | AE3: 3 | AF3: 10 | AG3: 7 | AH3: 1 | AI3: 7
A4: 37 | B4: Yes | C4: Travel_Rarely | D4: 1373 | E4: Research & Development | F4: 2 | G4: 2 | H4: Other | I4: 1 | J4: 4 | K4: 4 | L4: Male | M4: 92 | N4: 2 | O4: 1 | P4: Laboratory Technician | Q4: 3 | R4: Single | S4: 2090 | T4: 2396 | U4: 6 | V4: Y | W4: Yes | X4: 15 | Y4: 3 | Z4: 2 | AA4: 80 | AB4: 0 | AC4: 7 | AD4: 3 | AE4: 3 | AF4: 0 | AG4: 0 | AH4: 0 | AI4: 0
A5: 33 | B5: No | C5: Travel_Frequently | D5: 1392 | E5: Research & Development | F5: 3 | G5: 4 | H5: Life Sciences | I5: 1 | J5: 5 | K5: 4 | L5: Female | M5: 56 | N5: 3 | O5: 1 | P5: Research Scientist | Q5: 3 | R5: Married | S5: 2909 | T5: 23159 | U5: 1 | V5: Y | W5: Yes | X5: 11 | Y5: 3 | Z5: 3 | AA5: 80 | AB5: 0 | AC5: 8 | AD5: 3 | AE5: 3 | AF5: 8 | AG5: 7 | AH5: 3 | AI5: 0
A6: 27 | B6: No | C6: Travel_Rarely | D6: 591 | E6: Research & Development | F6: 2 | G6: 1 | H6: Medical | I6: 1 | J6: 7 | K6: 1 | L6: Male | M6: 40 | N6: 3 | O6: 1 | P6: Laboratory Technician | Q6: 2 | R6: Married | S6: 3468 | T6: 16632 | U6: 9 | V6: Y | W6: No | X6: 12 | Y6: 3 | Z6: 4 | AA6: 80 | AB6: 1 | AC6: 6 | AD6: 3 | AE6: 3 | AF6: 2 | AG6: 2 | AH6: 2 | AI6: 2
A7: 32 | B7: No | C7: Travel_Frequently | D7: 1005 | E7: Research & Development | F7: 2 | G7: 2 | H7: Life Sciences | I7: 1 | J7: 8 | K7: 4 | L7: Male | M7: 79 | N7: 3 | O7: 1 | P7: Laboratory Technician | Q7: 4 | R7: Single | S7: 3068 | T7: 11864 | U7: 0 | V7: Y | W7: No | X7: 13 | Y7: 3 | Z7: 3 | AA7: 80 | AB7: 0 | AC7: 8 | AD7: 2 | AE7: 2 | AF7: 7 | AG7: 7 | AH7: 3 | AI7: 6
A8: 59 | B8: No | C8: Travel_Rarely | D8: 1324 | E8: Research & Development | F8: 3 | G8: 3 | H8: Medical | I8: 1 | J8: 10 | K8: 3 | L8: Female | M8: 81 | N8: 4 | O8: 1 | P8: Laboratory Technician | Q8: 1 | R8: Married | S8: 2670 | T8: 9964 | U8: 4 | V8: Y | W8: Yes | X8: 20 | Y8: 4 | Z8: 1 | AA8: 80 | AB8: 3 | AC8: 12 | AD8: 3 | AE8: 2 | AF8: 1 | AG8: 0 | AH8: 0 | AI8: 0
A9: 30 | B9: No | C9: Travel_Rarely | D9: 1358 | E9: Research & Development | F9: 24 | G9: 1 | H9: Life Sciences | I9: 1 | J9: 11 | K9: 4 | L9: Male | M9: 67 | N9: 3 | O9: 1 | P9: Laboratory Technician | Q9: 3 | R9: Divorced | S9: 2693 | T9: 13335 | U9: 1 | V9: Y | W9: No | X9: 22 | Y9: 4 | Z9: 2 | AA9: 80 | AB9: 1 | AC9: 1 | AD9: 2 | AE9: 3 | AF9: 1 | AG9: 0 | AH9: 0 | AI9: 0
A10: 38 | B10: No | C10: Travel_Frequently | D10: 216 | E10: Research & Development | F10: 23 | G10: 3 | H10: Life Sciences | I10: 1 | J10: 12 | K10: 4 | L10: Male | M10: 44 | N10: 2 | O10: 3 | P10: Manufacturing Director | Q10: 3 | R10: Single | S10: 9526 | T10: 8787 | U10: 0 | V10: Y | W10: No | X10: 21 | Y10: 4 | Z10: 2 | AA10: 80 | AB10: 0 | AC10: 10 | AD10: 2 | AE10: 3 | AF10: 9 | AG10: 7 | AH10: 1 | AI10: 8
A11: 36 | B11: No | C11: Travel_Rarely | D11: 1299 | E11: Research & Development | F11: 27 | G11: 3 | H11: Medical | I11: 1 | J11: 13 | K11: 3 | L11: Male | M11: 94 | N11: 3 | O11: 2 | P11: Healthcare Representative | Q11: 3 | R11: Married | S11: 5237 | T11: 16577 | U11: 6 | V11: Y | W11: No | X11: 13 | Y11: 3 | Z11: 2 | AA11: 80 | AB11: 2 | AC11: 17 | AD11: 3 | AE11: 2 | AF11: 7 | AG11: 7 | AH11: 7 | AI11: 7
A12: 35 | B12: No | C12: Travel_Rarely | D12: 809 | E12: Research & Development | F12: 16 | G12: 3 | H12: Medical | I12: 1 | J12: 14 | K12: 1 | L12: Male | M12: 84 | N12: 4 | O12: 1 | P12: Laboratory Technician | Q12: 2 | R12: Married | S12: 2426 | T12: 16479 | U12: 0 | V12: Y | W12: No | X12: 13 | Y12: 3 | Z12: 3 | AA12: 80 | AB12: 1 | AC12: 6 | AD12: 5 | AE12: 3 | AF12: 5 | AG12: 4 | AH12: 0 | AI12: 3
A13: 29 | B13: No | C13: Travel_Rarely | D13: 153 | E13: Research & Development | F13: 15 | G13: 2 | H13: Life Sciences | I13: 1 | J13: 15 | K13: 4 | L13: Female | M13: 49 | N13: 2 | O13: 2 | P13: Laboratory Technician | Q13: 3 | R13: Single | S13: 4193 | T13: 12682 | U13: 0 | V13: Y | W13: Yes | X13: 12 | Y13: 3 | Z13: 4 | AA13: 80 | AB13: 0 | AC13: 10 | AD13: 3 | AE13: 3 | AF13: 9 | AG13: 5 | AH13: 0 | AI13: 8
... A1471: 34 | B1471: No | C1471: Travel_Rarely | D1471: 628 | E1471: Research & Development | F1471: 8 | G1471: 3 | H1471: Medical | I1471: 1 | J1471: 2068 | K1471: 2 | L1471: Male | M1471: 82 | N1471: 4 | O1471: 2 | P1471: Laboratory Technician | Q1471: 3 | R1471: Married | S1471: 4404 | T1471: 10228 | U1471: 2 | V1471: Y | W1471: No | X1471: 12 | Y1471: 3 | Z1471: 1 | AA1471: 80 | AB1471: 0 | AC1471: 6 | AD1471: 3 | AE1471: 4 | AF1471: 4 | AG1471: 3 | AH1471: 1 | AI1471: 2

Sheet Cleaned_Data
A1: Age | B1: Attrition | C1: BusinessTravel | D1: DailyRate | E1: Department | F1: DistanceFromHome | G1: Education | H1: EducationField | I1: EmployeeCount | J1: EmployeeNumber | K1: EnvironmentSatisfaction | L1: Gender | M1: HourlyRate | N1: JobInvolvement | O1: JobLevel | P1: JobRole | Q1: JobSatisfaction | R1: MaritalStatus | S1: MonthlyIncome | T1: MonthlyRate | U1: NumCompaniesWorked | V1: Over18 | W1: OverTime | X1: PercentSalaryHike | Y1: PerformanceRating | Z1: RelationshipSatisfaction | AA1: StandardHours | AB1: StockOptionLevel | AC1: TotalWorkingYears | AD1: TrainingTimesLastYear | AE1: WorkLifeBalance | AF1: YearsAtCompany | AG1: YearsInCurrentRole | AH1: YearsSinceLastPromotion | AI1: YearsWithCurrManager | AJ1: Attrition_Flag | AK1: Active_Flag | AL1: Age_Group | AM1: Salary_Band | AN1: Experience_Band | AO1: JobSatisfaction_Label | AP1: WorkLifeBalance_Label
A2: 41 | B2: Yes | C2: Travel_Rarely | D2: 1102 | E2: Sales | F2: 1 | G2: 2 | H2: Life Sciences | I2: 1 | J2: 1 | K2: 2 | L2: Female | M2: 94 | N2: 3 | O2: 2 | P2: Sales Executive | Q2: 4 | R2: Single | S2: 5993 | T2: 19479 | U2: 8 | V2: Y | W2: Yes | X2: 11 | Y2: 3 | Z2: 1 | AA2: 80 | AB2: 0 | AC2: 8 | AD2: 0 | AE2: 1 | AF2: 6 | AG2: 4 | AH2: 0 | AI2: 5 | AJ2: =IF(HR_Data[[#This Row],[Attrition]]="Yes",1,0) -> 1 | AK2: =IF(HR_Data[[#This Row],[Attrition]]="No",1,0) -> 0 | AL2: =IF(HR_Data[[#This Row],[Age]]<25,"Under 25",IF(HR_Data[[#This Row],[Age]]<=34,"25-34",IF(HR_Data[[#This Row],[Age]]<=44,"35-44",IF(HR_Data[[#This Row],[Age]]<=54,"45-54","55+")))) -> 35-44 | AM2: =IF(HR_Data[[#This Row],[MonthlyIncome]]<3000,"Low Salary",IF(HR_Data[[#This Row],[MonthlyIncome]]<=7000,"Medium Salary","High Salary")) -> Medium Salary | AN2: =IF(HR_Data[[#This Row],[YearsAtCompany]]<2,"0-1 Years",IF(HR_Data[[#This Row],[YearsAtCompany]]<=5,"2-5 Years",IF(HR_Data[[#This Row],[YearsAtCompany]]<=10,"6-10 Years","10+ Years"))) -> 6-10 Years | AO2: =IF(HR_Data[[#This Row],[JobSatisfaction]]=1,"Low",IF(HR_Data[[#This Row],[JobSatisfaction]]=2,"Medium",IF(HR_Data[[#This Row],[JobSatisfaction]]=3,"High","Very High"))) -> Very High | AP2: =IF(HR_Data[[#This Row],[WorkLifeBalance]]=1,"Bad",IF(HR_Data[[#This Row],[WorkLifeBalance]]=2,"Good",IF(HR_Data[[#This Row],[WorkLifeBalance]]=3,"Better","Best"))) -> Bad
A3: 49 | B3: No | C3: Travel_Frequently | D3: 279 | E3: Research & Development | F3: 8 | G3: 1 | H3: Life Sciences | I3: 1 | J3: 2 | K3: 3 | L3: Male | M3: 61 | N3: 2 | O3: 2 | P3: Research Scientist | Q3: 2 | R3: Married | S3: 5130 | T3: 24907 | U3: 1 | V3: Y | W3: No | X3: 23 | Y3: 4 | Z3: 4 | AA3: 80 | AB3: 1 | AC3: 10 | AD3: 3 | AE3: 3 | AF3: 10 | AG3: 7 | AH3: 1 | AI3: 7 | AJ3: =IF(HR_Data[[#This Row],[Attrition]]="Yes",1,0) -> 0 | AK3: =IF(HR_Data[[#This Row],[Attrition]]="No",1,0) -> 1 | AL3: =IF(HR_Data[[#This Row],[Age]]<25,"Under 25",IF(HR_Data[[#This Row],[Age]]<=34,"25-34",IF(HR_Data[[#This Row],[Age]]<=44,"35-44",IF(HR_Data[[#This Row],[Age]]<=54,"45-54","55+")))) -> 45-54 | AM3: =IF(HR_Data[[#This Row],[MonthlyIncome]]<3000,"Low Salary",IF(HR_Data[[#This Row],[MonthlyIncome]]<=7000,"Medium Salary","High Salary")) -> Medium Salary | AN3: =IF(HR_Data[[#This Row],[YearsAtCompany]]<2,"0-1 Years",IF(HR_Data[[#This Row],[YearsAtCompany]]<=5,"2-5 Years",IF(HR_Data[[#This Row],[YearsAtCompany]]<=10,"6-10 Years","10+ Years"))) -> 6-10 Years | AO3: =IF(HR_Data[[#This Row],[JobSatisfaction]]=1,"Low",IF(HR_Data[[#This Row],[JobSatisfaction]]=2,"Medium",IF(HR_Data[[#This Row],[JobSatisfaction]]=3,"High","Very High"))) -> Medium | AP3: =IF(HR_Data[[#This Row],[WorkLifeBalance]]=1,"Bad",IF(HR_Data[[#This Row],[WorkLifeBalance]]=2,"Good",IF(HR_Data[[#This Row],[WorkLifeBalance]]=3,"Better","Best"))) -> Better
A4: 37 | B4: Yes | C4: Travel_Rarely | D4: 1373 | E4: Research & Development | F4: 2 | G4: 2 | H4: Other | I4: 1 | J4: 4 | K4: 4 | L4: Male | M4: 92 | N4: 2 | O4: 1 | P4: Laboratory Technician | Q4: 3 | R4: Single | S4: 2090 | T4: 2396 | U4: 6 | V4: Y | W4: Yes | X4: 15 | Y4: 3 | Z4: 2 | AA4: 80 | AB4: 0 | AC4: 7 | AD4: 3 | AE4: 3 | AF4: 0 | AG4: 0 | AH4: 0 | AI4: 0 | AJ4: =IF(HR_Data[[#This Row],[Attrition]]="Yes",1,0) -> 1 | AK4: =IF(HR_Data[[#This Row],[Attrition]]="No",1,0) -> 0 | AL4: =IF(HR_Data[[#This Row],[Age]]<25,"Under 25",IF(HR_Data[[#This Row],[Age]]<=34,"25-34",IF(HR_Data[[#This Row],[Age]]<=44,"35-44",IF(HR_Data[[#This Row],[Age]]<=54,"45-54","55+")))) -> 35-44 | AM4: =IF(HR_Data[[#This Row],[MonthlyIncome]]<3000,"Low Salary",IF(HR_Data[[#This Row],[MonthlyIncome]]<=7000,"Medium Salary","High Salary")) -> Low Salary | AN4: =IF(HR_Data[[#This Row],[YearsAtCompany]]<2,"0-1 Years",IF(HR_Data[[#This Row],[YearsAtCompany]]<=5,"2-5 Years",IF(HR_Data[[#This Row],[YearsAtCompany]]<=10,"6-10 Years","10+ Years"))) -> 0-1 Years | AO4: =IF(HR_Data[[#This Row],[JobSatisfaction]]=1,"Low",IF(HR_Data[[#This Row],[JobSatisfaction]]=2,"Medium",IF(HR_Data[[#This Row],[JobSatisfaction]]=3,"High","Very High"))) -> High | AP4: =IF(HR_Data[[#This Row],[WorkLifeBalance]]=1,"Bad",IF(HR_Data[[#This Row],[WorkLifeBalance]]=2,"Good",IF(HR_Data[[#This Row],[WorkLifeBalance]]=3,"Better","Best"))) -> Better
A5: 33 | B5: No | C5: Travel_Frequently | D5: 1392 | E5: Research & Development | F5: 3 | G5: 4 | H5: Life Sciences | I5: 1 | J5: 5 | K5: 4 | L5: Female | M5: 56 | N5: 3 | O5: 1 | P5: Research Scientist | Q5: 3 | R5: Married | S5: 2909 | T5: 23159 | U5: 1 | V5: Y | W5: Yes | X5: 11 | Y5: 3 | Z5: 3 | AA5: 80 | AB5: 0 | AC5: 8 | AD5: 3 | AE5: 3 | AF5: 8 | AG5: 7 | AH5: 3 | AI5: 0 | AJ5: =IF(HR_Data[[#This Row],[Attrition]]="Yes",1,0) -> 0 | AK5: =IF(HR_Data[[#This Row],[Attrition]]="No",1,0) -> 1 | AL5: =IF(HR_Data[[#This Row],[Age]]<25,"Under 25",IF(HR_Data[[#This Row],[Age]]<=34,"25-34",IF(HR_Data[[#This Row],[Age]]<=44,"35-44",IF(HR_Data[[#This Row],[Age]]<=54,"45-54","55+")))) -> 25-34 | AM5: =IF(HR_Data[[#This Row],[MonthlyIncome]]<3000,"Low Salary",IF(HR_Data[[#This Row],[MonthlyIncome]]<=7000,"Medium Salary","High Salary")) -> Low Salary | AN5: =IF(HR_Data[[#This Row],[YearsAtCompany]]<2,"0-1 Years",IF(HR_Data[[#This Row],[YearsAtCompany]]<=5,"2-5 Years",IF(HR_Data[[#This Row],[YearsAtCompany]]<=10,"6-10 Years","10+ Years"))) -> 6-10 Years | AO5: =IF(HR_Data[[#This Row],[JobSatisfaction]]=1,"Low",IF(HR_Data[[#This Row],[JobSatisfaction]]=2,"Medium",IF(HR_Data[[#This Row],[JobSatisfaction]]=3,"High","Very High"))) -> High | AP5: =IF(HR_Data[[#This Row],[WorkLifeBalance]]=1,"Bad",IF(HR_Data[[#This Row],[WorkLifeBalance]]=2,"Good",IF(HR_Data[[#This Row],[WorkLifeBalance]]=3,"Better","Best"))) -> Better
A6: 27 | B6: No | C6: Travel_Rarely | D6: 591 | E6: Research & Development | F6: 2 | G6: 1 | H6: Medical | I6: 1 | J6: 7 | K6: 1 | L6: Male | M6: 40 | N6: 3 | O6: 1 | P6: Laboratory Technician | Q6: 2 | R6: Married | S6: 3468 | T6: 16632 | U6: 9 | V6: Y | W6: No | X6: 12 | Y6: 3 | Z6: 4 | AA6: 80 | AB6: 1 | AC6: 6 | AD6: 3 | AE6: 3 | AF6: 2 | AG6: 2 | AH6: 2 | AI6: 2 | AJ6: =IF(HR_Data[[#This Row],[Attrition]]="Yes",1,0) -> 0 | AK6: =IF(HR_Data[[#This Row],[Attrition]]="No",1,0) -> 1 | AL6: =IF(HR_Data[[#This Row],[Age]]<25,"Under 25",IF(HR_Data[[#This Row],[Age]]<=34,"25-34",IF(HR_Data[[#This Row],[Age]]<=44,"35-44",IF(HR_Data[[#This Row],[Age]]<=54,"45-54","55+")))) -> 25-34 | AM6: =IF(HR_Data[[#This Row],[MonthlyIncome]]<3000,"Low Salary",IF(HR_Data[[#This Row],[MonthlyIncome]]<=7000,"Medium Salary","High Salary")) -> Medium Salary | AN6: =IF(HR_Data[[#This Row],[YearsAtCompany]]<2,"0-1 Years",IF(HR_Data[[#This Row],[YearsAtCompany]]<=5,"2-5 Years",IF(HR_Data[[#This Row],[YearsAtCompany]]<=10,"6-10 Years","10+ Years"))) -> 2-5 Years | AO6: =IF(HR_Data[[#This Row],[JobSatisfaction]]=1,"Low",IF(HR_Data[[#This Row],[JobSatisfaction]]=2,"Medium",IF(HR_Data[[#This Row],[JobSatisfaction]]=3,"High","Very High"))) -> Medium | AP6: =IF(HR_Data[[#This Row],[WorkLifeBalance]]=1,"Bad",IF(HR_Data[[#This Row],[WorkLifeBalance]]=2,"Good",IF(HR_Data[[#This Row],[WorkLifeBalance]]=3,"Better","Best"))) -> Better
A7: 32 | B7: No | C7: Travel_Frequently | D7: 1005 | E7: Research & Development | F7: 2 | G7: 2 | H7: Life Sciences | I7: 1 | J7: 8 | K7: 4 | L7: Male | M7: 79 | N7: 3 | O7: 1 | P7: Laboratory Technician | Q7: 4 | R7: Single | S7: 3068 | T7: 11864 | U7: 0 | V7: Y | W7: No | X7: 13 | Y7: 3 | Z7: 3 | AA7: 80 | AB7: 0 | AC7: 8 | AD7: 2 | AE7: 2 | AF7: 7 | AG7: 7 | AH7: 3 | AI7: 6 | AJ7: =IF(HR_Data[[#This Row],[Attrition]]="Yes",1,0) -> 0 | AK7: =IF(HR_Data[[#This Row],[Attrition]]="No",1,0) -> 1 | AL7: =IF(HR_Data[[#This Row],[Age]]<25,"Under 25",IF(HR_Data[[#This Row],[Age]]<=34,"25-34",IF(HR_Data[[#This Row],[Age]]<=44,"35-44",IF(HR_Data[[#This Row],[Age]]<=54,"45-54","55+")))) -> 25-34 | AM7: =IF(HR_Data[[#This Row],[MonthlyIncome]]<3000,"Low Salary",IF(HR_Data[[#This Row],[MonthlyIncome]]<=7000,"Medium Salary","High Salary")) -> Medium Salary | AN7: =IF(HR_Data[[#This Row],[YearsAtCompany]]<2,"0-1 Years",IF(HR_Data[[#This Row],[YearsAtCompany]]<=5,"2-5 Years",IF(HR_Data[[#This Row],[YearsAtCompany]]<=10,"6-10 Years","10+ Years"))) -> 6-10 Years | AO7: =IF(HR_Data[[#This Row],[JobSatisfaction]]=1,"Low",IF(HR_Data[[#This Row],[JobSatisfaction]]=2,"Medium",IF(HR_Data[[#This Row],[JobSatisfaction]]=3,"High","Very High"))) -> Very High | AP7: =IF(HR_Data[[#This Row],[WorkLifeBalance]]=1,"Bad",IF(HR_Data[[#This Row],[WorkLifeBalance]]=2,"Good",IF(HR_Data[[#This Row],[WorkLifeBalance]]=3,"Better","Best"))) -> Good
A8: 59 | B8: No | C8: Travel_Rarely | D8: 1324 | E8: Research & Development | F8: 3 | G8: 3 | H8: Medical | I8: 1 | J8: 10 | K8: 3 | L8: Female | M8: 81 | N8: 4 | O8: 1 | P8: Laboratory Technician | Q8: 1 | R8: Married | S8: 2670 | T8: 9964 | U8: 4 | V8: Y | W8: Yes | X8: 20 | Y8: 4 | Z8: 1 | AA8: 80 | AB8: 3 | AC8: 12 | AD8: 3 | AE8: 2 | AF8: 1 | AG8: 0 | AH8: 0 | AI8: 0 | AJ8: =IF(HR_Data[[#This Row],[Attrition]]="Yes",1,0) -> 0 | AK8: =IF(HR_Data[[#This Row],[Attrition]]="No",1,0) -> 1 | AL8: =IF(HR_Data[[#This Row],[Age]]<25,"Under 25",IF(HR_Data[[#This Row],[Age]]<=34,"25-34",IF(HR_Data[[#This Row],[Age]]<=44,"35-44",IF(HR_Data[[#This Row],[Age]]<=54,"45-54","55+")))) -> 55+ | AM8: =IF(HR_Data[[#This Row],[MonthlyIncome]]<3000,"Low Salary",IF(HR_Data[[#This Row],[MonthlyIncome]]<=7000,"Medium Salary","High Salary")) -> Low Salary | AN8: =IF(HR_Data[[#This Row],[YearsAtCompany]]<2,"0-1 Years",IF(HR_Data[[#This Row],[YearsAtCompany]]<=5,"2-5 Years",IF(HR_Data[[#This Row],[YearsAtCompany]]<=10,"6-10 Years","10+ Years"))) -> 0-1 Years | AO8: =IF(HR_Data[[#This Row],[JobSatisfaction]]=1,"Low",IF(HR_Data[[#This Row],[JobSatisfaction]]=2,"Medium",IF(HR_Data[[#This Row],[JobSatisfaction]]=3,"High","Very High"))) -> Low | AP8: =IF(HR_Data[[#This Row],[WorkLifeBalance]]=1,"Bad",IF(HR_Data[[#This Row],[WorkLifeBalance]]=2,"Good",IF(HR_Data[[#This Row],[WorkLifeBalance]]=3,"Better","Best"))) -> Good
A9: 30 | B9: No | C9: Travel_Rarely | D9: 1358 | E9: Research & Development | F9: 24 | G9: 1 | H9: Life Sciences | I9: 1 | J9: 11 | K9: 4 | L9: Male | M9: 67 | N9: 3 | O9: 1 | P9: Laboratory Technician | Q9: 3 | R9: Divorced | S9: 2693 | T9: 13335 | U9: 1 | V9: Y | W9: No | X9: 22 | Y9: 4 | Z9: 2 | AA9: 80 | AB9: 1 | AC9: 1 | AD9: 2 | AE9: 3 | AF9: 1 | AG9: 0 | AH9: 0 | AI9: 0 | AJ9: =IF(HR_Data[[#This Row],[Attrition]]="Yes",1,0) -> 0 | AK9: =IF(HR_Data[[#This Row],[Attrition]]="No",1,0) -> 1 | AL9: =IF(HR_Data[[#This Row],[Age]]<25,"Under 25",IF(HR_Data[[#This Row],[Age]]<=34,"25-34",IF(HR_Data[[#This Row],[Age]]<=44,"35-44",IF(HR_Data[[#This Row],[Age]]<=54,"45-54","55+")))) -> 25-34 | AM9: =IF(HR_Data[[#This Row],[MonthlyIncome]]<3000,"Low Salary",IF(HR_Data[[#This Row],[MonthlyIncome]]<=7000,"Medium Salary","High Salary")) -> Low Salary | AN9: =IF(HR_Data[[#This Row],[YearsAtCompany]]<2,"0-1 Years",IF(HR_Data[[#This Row],[YearsAtCompany]]<=5,"2-5 Years",IF(HR_Data[[#This Row],[YearsAtCompany]]<=10,"6-10 Years","10+ Years"))) -> 0-1 Years | AO9: =IF(HR_Data[[#This Row],[JobSatisfaction]]=1,"Low",IF(HR_Data[[#This Row],[JobSatisfaction]]=2,"Medium",IF(HR_Data[[#This Row],[JobSatisfaction]]=3,"High","Very High"))) -> High | AP9: =IF(HR_Data[[#This Row],[WorkLifeBalance]]=1,"Bad",IF(HR_Data[[#This Row],[WorkLifeBalance]]=2,"Good",IF(HR_Data[[#This Row],[WorkLifeBalance]]=3,"Better","Best"))) -> Better
A10: 38 | B10: No | C10: Travel_Frequently | D10: 216 | E10: Research & Development | F10: 23 | G10: 3 | H10: Life Sciences | I10: 1 | J10: 12 | K10: 4 | L10: Male | M10: 44 | N10: 2 | O10: 3 | P10: Manufacturing Director | Q10: 3 | R10: Single | S10: 9526 | T10: 8787 | U10: 0 | V10: Y | W10: No | X10: 21 | Y10: 4 | Z10: 2 | AA10: 80 | AB10: 0 | AC10: 10 | AD10: 2 | AE10: 3 | AF10: 9 | AG10: 7 | AH10: 1 | AI10: 8 | AJ10: =IF(HR_Data[[#This Row],[Attrition]]="Yes",1,0) -> 0 | AK10: =IF(HR_Data[[#This Row],[Attrition]]="No",1,0) -> 1 | AL10: =IF(HR_Data[[#This Row],[Age]]<25,"Under 25",IF(HR_Data[[#This Row],[Age]]<=34,"25-34",IF(HR_Data[[#This Row],[Age]]<=44,"35-44",IF(HR_Data[[#This Row],[Age]]<=54,"45-54","55+")))) -> 35-44 | AM10: =IF(HR_Data[[#This Row],[MonthlyIncome]]<3000,"Low Salary",IF(HR_Data[[#This Row],[MonthlyIncome]]<=7000,"Medium Salary","High Salary")) -> High Salary | AN10: =IF(HR_Data[[#This Row],[YearsAtCompany]]<2,"0-1 Years",IF(HR_Data[[#This Row],[YearsAtCompany]]<=5,"2-5 Years",IF(HR_Data[[#This Row],[YearsAtCompany]]<=10,"6-10 Years","10+ Years"))) -> 6-10 Years | AO10: =IF(HR_Data[[#This Row],[JobSatisfaction]]=1,"Low",IF(HR_Data[[#This Row],[JobSatisfaction]]=2,"Medium",IF(HR_Data[[#This Row],[JobSatisfaction]]=3,"High","Very High"))) -> High | AP10: =IF(HR_Data[[#This Row],[WorkLifeBalance]]=1,"Bad",IF(HR_Data[[#This Row],[WorkLifeBalance]]=2,"Good",IF(HR_Data[[#This Row],[WorkLifeBalance]]=3,"Better","Best"))) -> Better
A11: 36 | B11: No | C11: Travel_Rarely | D11: 1299 | E11: Research & Development | F11: 27 | G11: 3 | H11: Medical | I11: 1 | J11: 13 | K11: 3 | L11: Male | M11: 94 | N11: 3 | O11: 2 | P11: Healthcare Representative | Q11: 3 | R11: Married | S11: 5237 | T11: 16577 | U11: 6 | V11: Y | W11: No | X11: 13 | Y11: 3 | Z11: 2 | AA11: 80 | AB11: 2 | AC11: 17 | AD11: 3 | AE11: 2 | AF11: 7 | AG11: 7 | AH11: 7 | AI11: 7 | AJ11: =IF(HR_Data[[#This Row],[Attrition]]="Yes",1,0) -> 0 | AK11: =IF(HR_Data[[#This Row],[Attrition]]="No",1,0) -> 1 | AL11: =IF(HR_Data[[#This Row],[Age]]<25,"Under 25",IF(HR_Data[[#This Row],[Age]]<=34,"25-34",IF(HR_Data[[#This Row],[Age]]<=44,"35-44",IF(HR_Data[[#This Row],[Age]]<=54,"45-54","55+")))) -> 35-44 | AM11: =IF(HR_Data[[#This Row],[MonthlyIncome]]<3000,"Low Salary",IF(HR_Data[[#This Row],[MonthlyIncome]]<=7000,"Medium Salary","High Salary")) -> Medium Salary | AN11: =IF(HR_Data[[#This Row],[YearsAtCompany]]<2,"0-1 Years",IF(HR_Data[[#This Row],[YearsAtCompany]]<=5,"2-5 Years",IF(HR_Data[[#This Row],[YearsAtCompany]]<=10,"6-10 Years","10+ Years"))) -> 6-10 Years | AO11: =IF(HR_Data[[#This Row],[JobSatisfaction]]=1,"Low",IF(HR_Data[[#This Row],[JobSatisfaction]]=2,"Medium",IF(HR_Data[[#This Row],[JobSatisfaction]]=3,"High","Very High"))) -> High | AP11: =IF(HR_Data[[#This Row],[WorkLifeBalance]]=1,"Bad",IF(HR_Data[[#This Row],[WorkLifeBalance]]=2,"Good",IF(HR_Data[[#This Row],[WorkLifeBalance]]=3,"Better","Best"))) -> Good
A12: 35 | B12: No | C12: Travel_Rarely | D12: 809 | E12: Research & Development | F12: 16 | G12: 3 | H12: Medical | I12: 1 | J12: 14 | K12: 1 | L12: Male | M12: 84 | N12: 4 | O12: 1 | P12: Laboratory Technician | Q12: 2 | R12: Married | S12: 2426 | T12: 16479 | U12: 0 | V12: Y | W12: No | X12: 13 | Y12: 3 | Z12: 3 | AA12: 80 | AB12: 1 | AC12: 6 | AD12: 5 | AE12: 3 | AF12: 5 | AG12: 4 | AH12: 0 | AI12: 3 | AJ12: =IF(HR_Data[[#This Row],[Attrition]]="Yes",1,0) -> 0 | AK12: =IF(HR_Data[[#This Row],[Attrition]]="No",1,0) -> 1 | AL12: =IF(HR_Data[[#This Row],[Age]]<25,"Under 25",IF(HR_Data[[#This Row],[Age]]<=34,"25-34",IF(HR_Data[[#This Row],[Age]]<=44,"35-44",IF(HR_Data[[#This Row],[Age]]<=54,"45-54","55+")))) -> 35-44 | AM12: =IF(HR_Data[[#This Row],[MonthlyIncome]]<3000,"Low Salary",IF(HR_Data[[#This Row],[MonthlyIncome]]<=7000,"Medium Salary","High Salary")) -> Low Salary | AN12: =IF(HR_Data[[#This Row],[YearsAtCompany]]<2,"0-1 Years",IF(HR_Data[[#This Row],[YearsAtCompany]]<=5,"2-5 Years",IF(HR_Data[[#This Row],[YearsAtCompany]]<=10,"6-10 Years","10+ Years"))) -> 2-5 Years | AO12: =IF(HR_Data[[#This Row],[JobSatisfaction]]=1,"Low",IF(HR_Data[[#This Row],[JobSatisfaction]]=2,"Medium",IF(HR_Data[[#This Row],[JobSatisfaction]]=3,"High","Very High"))) -> Medium | AP12: =IF(HR_Data[[#This Row],[WorkLifeBalance]]=1,"Bad",IF(HR_Data[[#This Row],[WorkLifeBalance]]=2,"Good",IF(HR_Data[[#This Row],[WorkLifeBalance]]=3,"Better","Best"))) -> Better
A13: 29 | B13: No | C13: Travel_Rarely | D13: 153 | E13: Research & Development | F13: 15 | G13: 2 | H13: Life Sciences | I13: 1 | J13: 15 | K13: 4 | L13: Female | M13: 49 | N13: 2 | O13: 2 | P13: Laboratory Technician | Q13: 3 | R13: Single | S13: 4193 | T13: 12682 | U13: 0 | V13: Y | W13: Yes | X13: 12 | Y13: 3 | Z13: 4 | AA13: 80 | AB13: 0 | AC13: 10 | AD13: 3 | AE13: 3 | AF13: 9 | AG13: 5 | AH13: 0 | AI13: 8 | AJ13: =IF(HR_Data[[#This Row],[Attrition]]="Yes",1,0) -> 0 | AK13: =IF(HR_Data[[#This Row],[Attrition]]="No",1,0) -> 1 | AL13: =IF(HR_Data[[#This Row],[Age]]<25,"Under 25",IF(HR_Data[[#This Row],[Age]]<=34,"25-34",IF(HR_Data[[#This Row],[Age]]<=44,"35-44",IF(HR_Data[[#This Row],[Age]]<=54,"45-54","55+")))) -> 25-34 | AM13: =IF(HR_Data[[#This Row],[MonthlyIncome]]<3000,"Low Salary",IF(HR_Data[[#This Row],[MonthlyIncome]]<=7000,"Medium Salary","High Salary")) -> Medium Salary | AN13: =IF(HR_Data[[#This Row],[YearsAtCompany]]<2,"0-1 Years",IF(HR_Data[[#This Row],[YearsAtCompany]]<=5,"2-5 Years",IF(HR_Data[[#This Row],[YearsAtCompany]]<=10,"6-10 Years","10+ Years"))) -> 6-10 Years | AO13: =IF(HR_Data[[#This Row],[JobSatisfaction]]=1,"Low",IF(HR_Data[[#This Row],[JobSatisfaction]]=2,"Medium",IF(HR_Data[[#This Row],[JobSatisfaction]]=3,"High","Very High"))) -> High | AP13: =IF(HR_Data[[#This Row],[WorkLifeBalance]]=1,"Bad",IF(HR_Data[[#This Row],[WorkLifeBalance]]=2,"Good",IF(HR_Data[[#This Row],[WorkLifeBalance]]=3,"Better","Best"))) -> Better
... A1471: 34 | B1471: No | C1471: Travel_Rarely | D1471: 628 | E1471: Research & Development | F1471: 8 | G1471: 3 | H1471: Medical | I1471: 1 | J1471: 2068 | K1471: 2 | L1471: Male | M1471: 82 | N1471: 4 | O1471: 2 | P1471: Laboratory Technician | Q1471: 3 | R1471: Married | S1471: 4404 | T1471: 10228 | U1471: 2 | V1471: Y | W1471: No | X1471: 12 | Y1471: 3 | Z1471: 1 | AA1471: 80 | AB1471: 0 | AC1471: 6 | AD1471: 3 | AE1471: 4 | AF1471: 4 | AG1471: 3 | AH1471: 1 | AI1471: 2 | AJ1471: =IF(HR_Data[[#This Row],[Attrition]]="Yes",1,0) -> 0 | AK1471: =IF(HR_Data[[#This Row],[Attrition]]="No",1,0) -> 1 | AL1471: =IF(HR_Data[[#This Row],[Age]]<25,"Under 25",IF(HR_Data[[#This Row],[Age]]<=34,"25-34",IF(HR_Data[[#This Row],[Age]]<=44,"35-44",IF(HR_Data[[#This Row],[Age]]<=54,"45-54","55+")))) -> 25-34 | AM1471: =IF(HR_Data[[#This Row],[MonthlyIncome]]<3000,"Low Salary",IF(HR_Data[[#This Row],[MonthlyIncome]]<=7000,"Medium Salary","High Salary")) -> Medium Salary | AN1471: =IF(HR_Data[[#This Row],[YearsAtCompany]]<2,"0-1 Years",IF(HR_Data[[#This Row],[YearsAtCompany]]<=5,"2-5 Years",IF(HR_Data[[#This Row],[YearsAtCompany]]<=10,"6-10 Years","10+ Years"))) -> 2-5 Years | AO1471: =IF(HR_Data[[#This Row],[JobSatisfaction]]=1,"Low",IF(HR_Data[[#This Row],[JobSatisfaction]]=2,"Medium",IF(HR_Data[[#This Row],[JobSatisfaction]]=3,"High","Very High"))) -> High | AP1471: =IF(HR_Data[[#This Row],[WorkLifeBalance]]=1,"Bad",IF(HR_Data[[#This Row],[WorkLifeBalance]]=2,"Good",IF(HR_Data[[#This Row],[WorkLifeBalance]]=3,"Better","Best"))) -> Best

Sheet Pivot_Analysis
A3: Total Employees | D3: Employees Left | G3: Active Employees | J3: Avg Monthly Income | M3: Attrition Rate
A4: 1470 | D4: 237 | G4: 1233 | J4: 6502.9313 | M4: =D4/A4 -> 0.16122449
A8: Department | B8: Employees Left | D8: Job Role | E8: Employees Left | H8: Age Group | I8: Employees Left | K8: Salary Band | L8: Employees Left
A9: Human Resources | B9: 12 | D9: Laboratory Technician | E9: 62 | H9: 25-34 | I9: 112 | K9: High Salary | L9: 47
A10: Research & Development | B10: 133 | D10: Sales Executive | E10: 57 | H10: 35-44 | I10: 51 | K10: Low Salary | L10: 113
A11: Sales | B11: 92 | D11: Research Scientist | E11: 47 | H11: 45-54 | I11: 25 | K11: Medium Salary | L11: 77
A12: Grand Total | B12: 237 | D12: Sales Representative | E12: 33 | H12: 55+ | I12: 11 | K12: Grand Total | L12: 237
D13: Human Resources | E13: 12 | H13: Under 25 | I13: 38
D14: Manufacturing Director | E14: 10 | H14: Grand Total | I14: 237
D15: Healthcare Representative | E15: 9
D16: Manager | E16: 5
D17: Research Director | E17: 2
D18: Grand Total | E18: 237 | H18: Department | I18: Total Employees | J18: Employees Left | K18: Attrition Rate | M18: Job Role | N18: Total Employees | O18: Employees Left | P18: Attrition Rate
H19: Sales | I19: 446 | J19: 92 | K19: 0.20627803 | M19: Sales Representative | N19: 83 | O19: 33 | P19: 0.39759036
H20: Human Resources | I20: 63 | J20: 12 | K20: 0.19047619 | M20: Laboratory Technician | N20: 259 | O20: 62 | P20: 0.23938224
H21: Research & Development | I21: 961 | J21: 133 | K21: 0.1383975 | M21: Human Resources | N21: 52 | O21: 12 | P21: 0.23076923
H22: Grand Total | I22: 1470 | J22: 237 | K22: 0.16122449 | M22: Sales Executive | N22: 326 | O22: 57 | P22: 0.17484663
M23: Research Scientist | N23: 292 | O23: 47 | P23: 0.1609589
M24: Manufacturing Director | N24: 145 | O24: 10 | P24: 0.068965517
M25: Healthcare Representative | N25: 131 | O25: 9 | P25: 0.06870229
B26: Overtime | C26: Attrition Rate | M26: Manager | N26: 102 | O26: 5 | P26: 0.049019608
B27: Yes | C27: 0.30528846 | M27: Research Director | N27: 80 | O27: 2 | P27: 0.025
B28: No | C28: 0.10436433 | M28: Grand Total | N28: 1470 | O28: 237 | P28: 0.16122449
B29: Grand Total | C29: 0.16122449
H31: Age Group | I31: Total Employees | J31: Employees Left | K31: Attrition Rate | M31: Salary Band | N31: Total Employees | O31: Employees Left | P31: Attrition Rate
H32: Under 25 | I32: 97 | J32: 38 | K32: 0.39175258 | M32: Low Salary | N32: 395 | O32: 113 | P32: 0.28607595
H33: 25-34 | I33: 554 | J33: 112 | K33: 0.20216606 | M33: Medium Salary | N33: 640 | O33: 77 | P33: 0.1203125
H34: 55+ | I34: 69 | J34: 11 | K34: 0.15942029 | M34: High Salary | N34: 435 | O34: 47 | P34: 0.10804598
H35: 45-54 | I35: 245 | J35: 25 | K35: 0.10204082 | M35: Grand Total | N35: 1470 | O35: 237 | P35: 0.16122449
H36: 35-44 | I36: 505 | J36: 51 | K36: 0.1009901
H37: Grand Total | I37: 1470 | J37: 237 | K37: 0.16122449
H40: OverTime | I40: Total Employees | J40: Employees Left | K40: Attrition Rate
H41: Yes | I41: 416 | J41: 127 | K41: 0.30528846
H42: No | I42: 1054 | J42: 110 | K42: 0.10436433
H43: Grand Total | I43: 1470 | J43: 237 | K43: 0.16122449
